README.txt
buildout.cfg
setup.py
src/zc/__init__.py
src/zc.monitorlogstats.egg-info/PKG-INFO
src/zc.monitorlogstats.egg-info/SOURCES.txt
src/zc.monitorlogstats.egg-info/dependency_links.txt
src/zc.monitorlogstats.egg-info/entry_points.txt
src/zc.monitorlogstats.egg-info/namespace_packages.txt
src/zc.monitorlogstats.egg-info/not-zip-safe
src/zc.monitorlogstats.egg-info/requires.txt
src/zc.monitorlogstats.egg-info/top_level.txt
src/zc/monitorlogstats/README.txt
src/zc/monitorlogstats/__init__.py
src/zc/monitorlogstats/component.xml
src/zc/monitorlogstats/configure.zcml
src/zc/monitorlogstats/tests.py
src/zc/monitorlogstats/zconfig.py