Metadata-Version: 1.0
Name: zc.monitorlogstats
Version: 0.1.0
Summary: Log handler and zc.z3monitor plugin to monitor log activity
Home-page: UNKNOWN
Author: Jim Fulton
Author-email: jim@zope.com
License: ZPL 2.1
Platform: UNKNOWN
